brynq_sdk_functions/__init__.py
brynq_sdk_functions/base_scenario_helper.py
brynq_sdk_functions/data_validation.py
brynq_sdk_functions/functions.py
brynq_sdk_functions/scenario_data_validator.py
brynq_sdk_functions/scenario_report_builder.py
brynq_sdk_functions-2.6.7.dev0.dist-info/METADATA
brynq_sdk_functions-2.6.7.dev0.dist-info/WHEEL
brynq_sdk_functions-2.6.7.dev0.dist-info/top_level.txt
brynq_sdk_functions-2.6.7.dev0.dist-info/RECORD
