Metadata-Version: 2.4
Name: brynq_sdk_functions
Version: 2.6.7.dev0
Summary: Helpful functions from BrynQ
Author: BrynQ
Author-email: support@brynq.com
License: BrynQ License
Requires-Dist: pandas<3,>=1
Requires-Dist: requests<=3,>=2
Requires-Dist: pyarrow>=10
Requires-Dist: pandera<=0.26.0
Requires-Dist: numpy<2
Dynamic: author
Dynamic: author-email
Dynamic: description
Dynamic: license
Dynamic: requires-dist
Dynamic: summary
